fxcmpy/LICENSE.txt
fxcmpy/__init__.py
fxcmpy/fxcmpy.py
fxcmpy/fxcmpy_closed_position.py
fxcmpy/fxcmpy_data_reader.py
fxcmpy/fxcmpy_instruments.py
fxcmpy/fxcmpy_oco_order.py
fxcmpy/fxcmpy_open_position.py
fxcmpy/fxcmpy_order.py
fxcmpy-1.3.3.dist-info/METADATA
fxcmpy-1.3.3.dist-info/WHEEL
fxcmpy-1.3.3.dist-info/top_level.txt
fxcmpy-1.3.3.dist-info/RECORD
