Metadata-Version: 1.2
Name: fxcmpy
Version: 1.3.3
Summary: A Python Wrapper Class for the RESTful API as provided by FXCM Forex Capital Markets Ltd.
Home-page: UNKNOWN
Author: FXCM API
Author-email: api@fxcm.com
License: BSD
Download-URL: https://pypi.org/project/fxcmpy/#files
Keywords: FXCM API Python Wrapper Finance Algo Trading
Platform: UNKNOWN
Classifier: Programming Language :: Python :: 3.4
Classifier: Programming Language :: Python :: 3.5
Classifier: Programming Language :: Python :: 3.6
Requires-Python: >=3.4
